gpp/__init__.py
gpp/actors/__init__.py
gpp/actors/gpp_sem_label_actor.py
gpp/actors/gpp_sem_model_actor.py
gpp/actors/graph_space_actor.py
gpp/actors/qa_llm_actor.py
gpp/config.py
gpp/llm/__init__.py
gpp/llm/qa_llm/__init__.py
gpp/llm/qa_llm/_base_agent.py
gpp/llm/qa_llm/_explicit_v100.py
gpp/llm/qa_llm/_hfmodels/__init__.py
gpp/llm/qa_llm/_hfmodels/__main__.py
gpp/llm/qa_llm/_hfmodels/_default.py
gpp/llm/qa_llm/_hfmodels/_gemma_2.py
gpp/llm/qa_llm/_hfmodels/_olmo.py
gpp/llm/qa_llm/_hugging_face_agent.py
gpp/llm/qa_llm/_input_table.py
gpp/llm/qa_llm/_schema.py
gpp/llm/qa_llm/_thread.py
gpp/sem_label/__init__.py
gpp/sem_label/data_modules/__init__.py
gpp/sem_label/data_modules/base.py
gpp/sem_label/data_modules/v210.py
gpp/sem_label/feat_store.py
gpp/sem_label/feat_store_fn.py
gpp/sem_label/feats/__init__.py
gpp/sem_label/feats/__main__.py
gpp/sem_label/feats/_example.py
gpp/sem_label/feats/_misc.py
gpp/sem_label/feats/_negative_label.py
gpp/sem_label/feats/_sample.py
gpp/sem_label/feats/_target_example.py
gpp/sem_label/feats/_target_example_embedding.py
gpp/sem_label/feats/_target_label.py
gpp/sem_label/feats/_target_label_embedding.py
gpp/sem_label/feats/_text_sample_fn.py
gpp/sem_label/isem_label.py
gpp/sem_label/model_usage/__init__.py
gpp/sem_label/model_usage/contrastive_v220.py
gpp/sem_label/models/__init__.py
gpp/sem_label/models/base.py
gpp/sem_label/models/contrastive/__init__.py
gpp/sem_label/models/contrastive/contrastive_v1.py
gpp/sem_label/models/contrastive/v220.py
gpp/sem_label/models/contrastive/v221.py
gpp/sem_label/models/llm.py
gpp/sem_label/models/precompute_model.py
gpp/sem_model/__init__.py
gpp/sem_model/from_sem_label/__init__.py
gpp/sem_model/from_sem_label/_algo_base.py
gpp/sem_model/from_sem_label/algo_v300.py
gpp/sem_model/from_sem_label/steiner_tree_v100.py
gpp/sem_model/from_sem_label/steiner_tree_v101.py
gpp/typing.py
gramsplusplus-1.0.4.dist-info/LICENSE
gramsplusplus-1.0.4.dist-info/METADATA
gramsplusplus-1.0.4.dist-info/WHEEL
gramsplusplus-1.0.4.dist-info/RECORD
