Metadata-Version: 2.1
Name: gramsplusplus
Version: 1.0.4
Summary: GRAMS++
License: MIT
Author: Binh Vu
Author-email: binh@toan2.com
Requires-Python: >=3.11,<4.0
Classifier: License :: OSI Approved :: MIT License
Classifier: Programming Language :: Python :: 3
Classifier: Programming Language :: Python :: 3.11
Classifier: Programming Language :: Python :: 3.12
Classifier: Programming Language :: Python :: 3.13
Requires-Dist: accelerate (>=1.3.0,<2.0.0)
Requires-Dist: keyvec (>=1.0.1,<2.0.0)
Requires-Dist: libactor (>=2.6.2,<3.0.0)
Requires-Dist: lightning (>=2.4.0,<3.0.0)
Requires-Dist: loguru (>=0.7.2,<0.8.0)
Requires-Dist: sem-desc (>=6.13.5,<7.0.0)
Requires-Dist: torch (>=2.4.1,<3.0.0)
Requires-Dist: torchmetrics (>=1.4.1,<2.0.0)
